comot_update_berita_terpopuler_detik/__init__.py
comot_update_berita_terpopuler_detik-0.3.dist-info/LICENSE
comot_update_berita_terpopuler_detik-0.3.dist-info/METADATA
comot_update_berita_terpopuler_detik-0.3.dist-info/WHEEL
comot_update_berita_terpopuler_detik-0.3.dist-info/top_level.txt
comot_update_berita_terpopuler_detik-0.3.dist-info/RECORD
